LICENSE.txt
MANIFEST.in
README.txt
requirements.txt.txt
setup.py
techai/__init__.py
techai.egg-info/PKG-INFO
techai.egg-info/SOURCES.txt
techai.egg-info/dependency_links.txt
techai.egg-info/requires.txt
techai.egg-info/top_level.txt