Metadata-Version: 2.1
Name: techai
Version: 2.3.3
Summary: can be used to make simple neural networks.
Home-page: 
Author: Technik
Author-email: makemyclick3@gmail.com
License: MIT
Keywords: Techai easy AI Tool
Platform: UNKNOWN
Classifier: Development Status :: 5 - Production/Stable
Classifier: Intended Audience :: Education
Classifier: Operating System :: Microsoft :: Windows :: Windows 10
Classifier: License :: OSI Approved :: MIT License
Classifier: Programming Language :: Python :: 3
License-File: LICENSE.txt
